requirements.txt
setup.py
django_remark42/__init__.py
django_remark42.egg-info/PKG-INFO
django_remark42.egg-info/SOURCES.txt
django_remark42.egg-info/dependency_links.txt
django_remark42.egg-info/requires.txt
django_remark42.egg-info/top_level.txt
django_remark42/templatetags/__init__.py
django_remark42/templatetags/remark42.py