Metadata-Version: 2.1
Name: django-remark42
Version: 2020.7.1
Summary: django remark42 comments
Home-page: https://github.com/andrewp-as-is/django-remark42.py
License: Unlicense
Keywords: django remark42 comments
Platform: UNKNOWN
Classifier: Framework :: Django
Classifier: License :: Public Domain
Classifier: Operating System :: OS Independent
Classifier: Programming Language :: Python :: 3
